anno2ls/__init__.py
anno2ls/core.py
anno2ls-0.1.0.dist-info/METADATA
anno2ls-0.1.0.dist-info/WHEEL
anno2ls-0.1.0.dist-info/top_level.txt
anno2ls-0.1.0.dist-info/RECORD
