Metadata-Version: 2.1
Name: anno2ls
Version: 0.1.0
Summary: Helper to import images and annotations to Label Studio
Home-page: https://github.com/Vaaaaaalllll/anno2ls
Author: Val Kenneth Arado
Author-email: aradovalkenneth@gmail.com
License: MIT
Platform: UNKNOWN
Classifier: License :: OSI Approved :: MIT License
Classifier: Programming Language :: Python :: 3
Classifier: Operating System :: OS Independent
Requires-Python: >=3.6
Requires-Dist: requests
